{
    "superruns": [
        {
            "runs": [
                {
                    "completedTotal": 4533466,
                    "failed": {
                        "deadlock": 0,
                        "concurrentWrite": 181519,
                        "dangerousStructure": 0
                    },
                    "completed": {
                        "RC": 0,
                        "SI": 4533466,
                        "SSI": 0
                    },
                    "programs": {
                        "balance": {
                            "failed": {
                                "deadlock": 0,
                                "concurrentWrite": 0,
                                "dangerousStructure": 0
                            },
                            "completed": {
                                "RC": 0,
                                "SI": 907746,
                                "SSI": 0
                            },
                            "runtime": 694.6746046543121
                        },
                        "amalgamate": {
                            "failed": {
                                "deadlock": 0,
                                "concurrentWrite": 76484,
                                "dangerousStructure": 0
                            },
                            "completed": {
                                "RC": 0,
                                "SI": 905670,
                                "SSI": 0
                            },
                            "runtime": 1795.2976067066193
                        },
                        "writeCheck": {
                            "failed": {
                                "deadlock": 0,
                                "concurrentWrite": 62073,
                                "dangerousStructure": 0
                            },
                            "completed": {
                                "RC": 0,
                                "SI": 906705,
                                "SSI": 0
                            },
                            "runtime": 1410.5970323085785
                        },
                        "depositChecking": {
                            "failed": {
                                "deadlock": 0,
                                "concurrentWrite": 23970,
                                "dangerousStructure": 0
                            },
                            "completed": {
                                "RC": 0,
                                "SI": 904938,
                                "SSI": 0
                            },
                            "runtime": 1000.6644062995911
                        },
                        "transactSavings": {
                            "failed": {
                                "deadlock": 0,
                                "concurrentWrite": 18992,
                                "dangerousStructure": 0
                            },
                            "completed": {
                                "RC": 0,
                                "SI": 908407,
                                "SSI": 0
                            },
                            "runtime": 1007.1442096233368
                        }
                    }
                }
            ]
        },
        {
            "runs": [
                {
                    "completedTotal": 4248333,
                    "failed": {
                        "deadlock": 0,
                        "concurrentWrite": 170946,
                        "dangerousStructure": 0
                    },
                    "completed": {
                        "RC": 0,
                        "SI": 4248333,
                        "SSI": 0
                    },
                    "programs": {
                        "balance": {
                            "failed": {
                                "deadlock": 0,
                                "concurrentWrite": 0,
                                "dangerousStructure": 0
                            },
                            "completed": {
                                "RC": 0,
                                "SI": 849571,
                                "SSI": 0
                            },
                            "runtime": 658.4800775051117
                        },
                        "transactSavings": {
                            "failed": {
                                "deadlock": 0,
                                "concurrentWrite": 17929,
                                "dangerousStructure": 0
                            },
                            "completed": {
                                "RC": 0,
                                "SI": 848808,
                                "SSI": 0
                            },
                            "runtime": 1004.6199903488159
                        },
                        "writeCheck": {
                            "failed": {
                                "deadlock": 0,
                                "concurrentWrite": 58967,
                                "dangerousStructure": 0
                            },
                            "completed": {
                                "RC": 0,
                                "SI": 851436,
                                "SSI": 0
                            },
                            "runtime": 1438.675437450409
                        },
                        "amalgamate": {
                            "failed": {
                                "deadlock": 0,
                                "concurrentWrite": 71398,
                                "dangerousStructure": 0
                            },
                            "completed": {
                                "RC": 0,
                                "SI": 848923,
                                "SSI": 0
                            },
                            "runtime": 1831.6947312355042
                        },
                        "depositChecking": {
                            "failed": {
                                "deadlock": 0,
                                "concurrentWrite": 22652,
                                "dangerousStructure": 0
                            },
                            "completed": {
                                "RC": 0,
                                "SI": 849595,
                                "SSI": 0
                            },
                            "runtime": 983.0707306861877
                        }
                    }
                }
            ]
        },
        {
            "runs": [
                {
                    "completedTotal": 4537892,
                    "failed": {
                        "deadlock": 0,
                        "concurrentWrite": 180849,
                        "dangerousStructure": 0
                    },
                    "completed": {
                        "RC": 0,
                        "SI": 4537892,
                        "SSI": 0
                    },
                    "programs": {
                        "writeCheck": {
                            "failed": {
                                "deadlock": 0,
                                "concurrentWrite": 62316,
                                "dangerousStructure": 0
                            },
                            "completed": {
                                "RC": 0,
                                "SI": 908572,
                                "SSI": 0
                            },
                            "runtime": 1409.651917219162
                        },
                        "depositChecking": {
                            "failed": {
                                "deadlock": 0,
                                "concurrentWrite": 23832,
                                "dangerousStructure": 0
                            },
                            "completed": {
                                "RC": 0,
                                "SI": 907570,
                                "SSI": 0
                            },
                            "runtime": 993.6418018341064
                        },
                        "balance": {
                            "failed": {
                                "deadlock": 0,
                                "concurrentWrite": 0,
                                "dangerousStructure": 0
                            },
                            "completed": {
                                "RC": 0,
                                "SI": 905932,
                                "SSI": 0
                            },
                            "runtime": 697.994579076767
                        },
                        "amalgamate": {
                            "failed": {
                                "deadlock": 0,
                                "concurrentWrite": 75697,
                                "dangerousStructure": 0
                            },
                            "completed": {
                                "RC": 0,
                                "SI": 908682,
                                "SSI": 0
                            },
                            "runtime": 1807.0606679916382
                        },
                        "transactSavings": {
                            "failed": {
                                "deadlock": 0,
                                "concurrentWrite": 19004,
                                "dangerousStructure": 0
                            },
                            "completed": {
                                "RC": 0,
                                "SI": 907136,
                                "SSI": 0
                            },
                            "runtime": 1002.0979583263397
                        }
                    }
                }
            ]
        },
        {
            "runs": [
                {
                    "completedTotal": 4499659,
                    "failed": {
                        "deadlock": 0,
                        "concurrentWrite": 180531,
                        "dangerousStructure": 0
                    },
                    "completed": {
                        "RC": 0,
                        "SI": 4499659,
                        "SSI": 0
                    },
                    "programs": {
                        "balance": {
                            "failed": {
                                "deadlock": 0,
                                "concurrentWrite": 0,
                                "dangerousStructure": 0
                            },
                            "completed": {
                                "RC": 0,
                                "SI": 900360,
                                "SSI": 0
                            },
                            "runtime": 697.1944551467896
                        },
                        "transactSavings": {
                            "failed": {
                                "deadlock": 0,
                                "concurrentWrite": 18744,
                                "dangerousStructure": 0
                            },
                            "completed": {
                                "RC": 0,
                                "SI": 899429,
                                "SSI": 0
                            },
                            "runtime": 1005.3598127365112
                        },
                        "depositChecking": {
                            "failed": {
                                "deadlock": 0,
                                "concurrentWrite": 23735,
                                "dangerousStructure": 0
                            },
                            "completed": {
                                "RC": 0,
                                "SI": 900855,
                                "SSI": 0
                            },
                            "runtime": 994.2423348426819
                        },
                        "amalgamate": {
                            "failed": {
                                "deadlock": 0,
                                "concurrentWrite": 75519,
                                "dangerousStructure": 0
                            },
                            "completed": {
                                "RC": 0,
                                "SI": 899842,
                                "SSI": 0
                            },
                            "runtime": 1804.170119524002
                        },
                        "writeCheck": {
                            "failed": {
                                "deadlock": 0,
                                "concurrentWrite": 62533,
                                "dangerousStructure": 0
                            },
                            "completed": {
                                "RC": 0,
                                "SI": 899173,
                                "SSI": 0
                            },
                            "runtime": 1408.6238856315613
                        }
                    }
                }
            ]
        },
        {
            "runs": [
                {
                    "completedTotal": 4439041,
                    "failed": {
                        "deadlock": 0,
                        "concurrentWrite": 178246,
                        "dangerousStructure": 0
                    },
                    "completed": {
                        "RC": 0,
                        "SI": 4439041,
                        "SSI": 0
                    },
                    "programs": {
                        "transactSavings": {
                            "failed": {
                                "deadlock": 0,
                                "concurrentWrite": 18261,
                                "dangerousStructure": 0
                            },
                            "completed": {
                                "RC": 0,
                                "SI": 887251,
                                "SSI": 0
                            },
                            "runtime": 1008.1707837581635
                        },
                        "balance": {
                            "failed": {
                                "deadlock": 0,
                                "concurrentWrite": 0,
                                "dangerousStructure": 0
                            },
                            "completed": {
                                "RC": 0,
                                "SI": 886472,
                                "SSI": 0
                            },
                            "runtime": 680.625846862793
                        },
                        "amalgamate": {
                            "failed": {
                                "deadlock": 0,
                                "concurrentWrite": 74444,
                                "dangerousStructure": 0
                            },
                            "completed": {
                                "RC": 0,
                                "SI": 888160,
                                "SSI": 0
                            },
                            "runtime": 1816.024099111557
                        },
                        "writeCheck": {
                            "failed": {
                                "deadlock": 0,
                                "concurrentWrite": 61721,
                                "dangerousStructure": 0
                            },
                            "completed": {
                                "RC": 0,
                                "SI": 888164,
                                "SSI": 0
                            },
                            "runtime": 1421.4210209846497
                        },
                        "depositChecking": {
                            "failed": {
                                "deadlock": 0,
                                "concurrentWrite": 23820,
                                "dangerousStructure": 0
                            },
                            "completed": {
                                "RC": 0,
                                "SI": 888994,
                                "SSI": 0
                            },
                            "runtime": 985.4638693332672
                        }
                    }
                }
            ]
        }
    ],
    "config": {
        "concurrentClients": 100,
        "dbUrl": "r27i27n21",
        "dbPort": 5432,
        "dbUsername": "postgres",
        "dbPassword": "postgres",
        "dbName": "postgres",
        "timing": {
            "warmup": 10,
            "experiment": 60,
            "extraTime": 5
        },
        "numberOfSuperruns": 5,
        "numberOfRuns": 1,
        "experimentName": "Promoted_0_23",
        "category": "non-optimal",
        "robust": "true",
        "benchmark": "smallBank",
        "smallBank": {
            "numberOfAccounts": 18000,
            "programDepositCheckingSamplingWeight": 1,
            "programDepositCheckingAllocatedIsolationLevel": "SI",
            "programBalanceSamplingWeight": 1,
            "programBalanceAllocatedIsolationLevel": "SI",
            "programBalanceIsPromoted": "false",
            "programTransactSavingsSamplingWeight": 1,
            "programTransactSavingsAllocatedIsolationLevel": "SI",
            "programAmalgamateSamplingWeight": 1,
            "programAmalgamateAllocatedIsolationLevel": "SI",
            "programWriteCheckSamplingWeight": 1,
            "programWriteCheckAllocatedIsolationLevel": "SI",
            "programWriteCheckIsPromoted": "SavingsChecking",
            "accountSamplingMethod": "hotspot",
            "hotspotProbability": 0.1,
            "hotspotSize": 20
        }
    }
}